example/main.py
topiq_utils-0.1.8.dist-info/licenses/LICENSE
topiqutils/auth/__init__.py
topiqutils/auth/jwt_auth.py
topiqutils/auth/__pycache__/__init__.cpython-311.pyc
topiqutils/auth/__pycache__/jwt.cpython-311.pyc
topiqutils/auth/__pycache__/jwt_auth.cpython-311.pyc
topiqutils/auth/middlewares/__init__.py
topiqutils/auth/middlewares/jwt_decode.py
topiqutils/auth/middlewares/__pycache__/__init__.cpython-311.pyc
topiqutils/auth/middlewares/__pycache__/jwt_decode.cpython-311.pyc
topiqutils/utils/__init__.py
topiqutils/utils/sample.py
topiq_utils-0.1.8.dist-info/METADATA
topiq_utils-0.1.8.dist-info/WHEEL
topiq_utils-0.1.8.dist-info/top_level.txt
topiq_utils-0.1.8.dist-info/RECORD
